stream2sentence/__init__.py
stream2sentence/avoid_pause_words.py
stream2sentence/delimiter_ignore_prefixes.py
stream2sentence/stream2sentence.py
stream2sentence/stream2sentence_time_based.py
stream2sentence-0.3.1.dist-info/METADATA
stream2sentence-0.3.1.dist-info/WHEEL
stream2sentence-0.3.1.dist-info/top_level.txt
stream2sentence-0.3.1.dist-info/RECORD
