Metadata-Version: 2.4
Name: stream2sentence
Version: 0.3.1
Summary: Real-time processing and delivery of sentences from a continuous stream of characters or text chunks.
Home-page: https://github.com/KoljaB/stream2sentence
Author: Kolja Beigel
Author-email: kolja.beigel@web.de
Keywords: realtime,text streaming,stream,sentence,sentence detection,sentence generation,tts,speech synthesis,nltk,text analysis,audio processing,boundary detection,sentence boundary detection
Classifier: Programming Language :: Python :: 3
Classifier: License :: OSI Approved :: MIT License
Classifier: Operating System :: OS Independent
Requires-Python: >=3.6
Requires-Dist: nltk==3.9.1
Requires-Dist: emoji==2.14.1
Requires-Dist: stanza==1.10.1
Dynamic: author
Dynamic: author-email
Dynamic: classifier
Dynamic: description
Dynamic: description-content-type
Dynamic: home-page
Dynamic: keywords
Dynamic: requires-dist
Dynamic: requires-python
Dynamic: summary
